{
  "available": true,
  "headline": "Spanien bewegt sich am staerksten: +9.2 Pkt. auf 24.6% Titelchance.",
  "last_game": "2026-07-06",
  "leader": {
    "name": "Spanien",
    "p_titel": 0.2463,
    "team": "Spanien"
  },
  "live_eval": {
    "basis": 1.0688,
    "beats_basis": true,
    "logloss": 0.857,
    "n": 72
  },
  "movers": [
    {
      "delta": 0.0922,
      "direction": "up",
      "name": "Spanien",
      "p_titel": 0.2463,
      "reasons": [
        "Live-Elo +13",
        "Gruppenweg fast offen"
      ],
      "team": "Spanien"
    },
    {
      "delta": -0.0647,
      "direction": "down",
      "name": "Portugal",
      "p_titel": 0.0,
      "reasons": [
        "Live-Elo -13",
        "Gruppenweg fast offen"
      ],
      "team": "Portugal"
    },
    {
      "delta": 0.0182,
      "direction": "up",
      "name": "Belgien",
      "p_titel": 0.0574,
      "reasons": [
        "Live-Elo +29",
        "Gruppenweg fast offen"
      ],
      "team": "Belgien"
    },
    {
      "delta": -0.0085,
      "direction": "down",
      "name": "Frankreich",
      "p_titel": 0.1556,
      "reasons": [
        "Gruppenweg fast offen"
      ],
      "team": "Frankreich"
    },
    {
      "delta": -0.0082,
      "direction": "down",
      "name": "Norwegen",
      "p_titel": 0.0674,
      "reasons": [
        "Live-Elo -11",
        "Gruppenweg fast offen"
      ],
      "team": "Norwegen"
    },
    {
      "delta": -0.0076,
      "direction": "down",
      "name": "USA",
      "p_titel": 0.0,
      "reasons": [
        "Live-Elo -29"
      ],
      "team": "USA"
    }
  ],
  "n_played": 94,
  "stamp": "2026-07-07 10:36",
  "top3": [
    {
      "name": "Spanien",
      "p_titel": 0.2463,
      "team": "Spanien"
    },
    {
      "name": "Argentinien",
      "p_titel": 0.1726,
      "team": "Argentinien"
    },
    {
      "name": "England",
      "p_titel": 0.1599,
      "team": "England"
    }
  ]
}
